vae_anomaly_detection/VAE.py
vae_anomaly_detection/VAE_tf1.py
vae_anomaly_detection/__init__.py
vae_anomaly_detection/encoder_decoder.py
vae_anomaly_detection-2.0.1.dist-info/METADATA
vae_anomaly_detection-2.0.1.dist-info/WHEEL
vae_anomaly_detection-2.0.1.dist-info/RECORD
