Metadata-Version: 2.1
Name: vae_anomaly_detection
Version: 2.0.1
Summary: Pytorch/TF1 implementation of Variational AutoEncoder for anomaly detection following the paper "Variational Autoencoder based Anomaly Detection using Reconstruction Probability by Jinwon An, Sungzoon Cho"
Project-URL: homepage, https://github.com/Michedev/VAE_anomaly_detection
Project-URL: repository, https://github.com/Michedev/VAE_anomaly_detection
Author-email: Michele De Vita <mik3dev@gmail.com>
License: MIT
Keywords: anomaly detection,deep learning,pytorch,vae
Classifier: Development Status :: 5 - Production/Stable
Classifier: Intended Audience :: Developers
Classifier: Intended Audience :: Science/Research
Classifier: License :: OSI Approved :: MIT License
Classifier: Operating System :: OS Independent
Classifier: Programming Language :: Python
Classifier: Programming Language :: Python :: 3
Classifier: Programming Language :: Python :: 3.7
Classifier: Programming Language :: Python :: 3.8
Classifier: Programming Language :: Python :: 3.9
Classifier: Programming Language :: Python :: 3.10
Classifier: Programming Language :: Python :: 3.11
Classifier: Topic :: Scientific/Engineering :: Artificial Intelligence
Classifier: Topic :: Software Development :: Libraries :: Python Modules
Requires-Python: <3.12,>3.6
Requires-Dist: numpy>=1.18
Requires-Dist: path>=15.0
Requires-Dist: pytorch-lightning>=1.9
Requires-Dist: pyyaml>=5.0
Requires-Dist: tensorboard>=0.20
Requires-Dist: torch>=1.8
Requires-Dist: tqdm>=4.0
Provides-Extra: dev
Requires-Dist: pytest; extra == 'dev'
